AUTHORS.rst
CHANGELOG.rst
LICENSE
MANIFEST.in
README.rst
setup.py
ckeditor/__init__.py
ckeditor/fields.py
ckeditor/image_processing.py
ckeditor/models.py
ckeditor/urls.py
ckeditor/utils.py
ckeditor/views.py
ckeditor/widgets.py
ckeditor/image/__init__.py
ckeditor/image/dummy_backend.py
ckeditor/image/pillow_backend.py
ckeditor/management/__init__.py
ckeditor/management/commands/__init__.py
ckeditor/management/commands/generateckeditorthumbnails.py
ckeditor/static/ckeditor/ckeditor/CHANGES.md
ckeditor/static/ckeditor/ckeditor/LICENSE.md
ckeditor/static/ckeditor/ckeditor/README.md
ckeditor/static/ckeditor/ckeditor/build-config.js
ckeditor/static/ckeditor/ckeditor/ckeditor.js
ckeditor/static/ckeditor/ckeditor/config.js
ckeditor/static/ckeditor/ckeditor/contents.css
ckeditor/static/ckeditor/ckeditor/styles.js
ckeditor/static/ckeditor/ckeditor/adapters/jquery.js
ckeditor/static/ckeditor/ckeditor/lang/af.js
ckeditor/static/ckeditor/ckeditor/lang/ar.js
ckeditor/static/ckeditor/ckeditor/lang/bg.js
ckeditor/static/ckeditor/ckeditor/lang/bn.js
ckeditor/static/ckeditor/ckeditor/lang/bs.js
ckeditor/static/ckeditor/ckeditor/lang/ca.js
ckeditor/static/ckeditor/ckeditor/lang/cs.js
ckeditor/static/ckeditor/ckeditor/lang/cy.js
ckeditor/static/ckeditor/ckeditor/lang/da.js
ckeditor/static/ckeditor/ckeditor/lang/de.js
ckeditor/static/ckeditor/ckeditor/lang/el.js
ckeditor/static/ckeditor/ckeditor/lang/en-au.js
ckeditor/static/ckeditor/ckeditor/lang/en-ca.js
ckeditor/static/ckeditor/ckeditor/lang/en-gb.js
ckeditor/static/ckeditor/ckeditor/lang/en.js
ckeditor/static/ckeditor/ckeditor/lang/eo.js
ckeditor/static/ckeditor/ckeditor/lang/es.js
ckeditor/static/ckeditor/ckeditor/lang/et.js
ckeditor/static/ckeditor/ckeditor/lang/eu.js
ckeditor/static/ckeditor/ckeditor/lang/fa.js
ckeditor/static/ckeditor/ckeditor/lang/fi.js
ckeditor/static/ckeditor/ckeditor/lang/fo.js
ckeditor/static/ckeditor/ckeditor/lang/fr-ca.js
ckeditor/static/ckeditor/ckeditor/lang/fr.js
django_ckeditor_updated.egg-info/PKG-INFO
django_ckeditor_updated.egg-info/SOURCES.txt
django_ckeditor_updated.egg-info/dependency_links.txt
django_ckeditor_updated.egg-info/requires.txt
django_ckeditor_updated.egg-info/top_level.txt