Metadata-Version: 1.1
Name: django-ckeditor-updated
Version: 4.4.0
Summary: Django admin CKEditor integration.
Home-page: https://github.com/riklaunim/django-ckeditor
Author: Piotr Malinski
Author-email: riklaunim@gmail.com
License: UNKNOWN
Platform: UNKNOWN
Classifier: Programming Language :: Python
Classifier: Programming Language :: Python :: 2.7
Classifier: Programming Language :: Python :: 3.3
Classifier: Programming Language :: Python :: 3.4
Classifier: License :: OSI Approved :: BSD License
Classifier: Operating System :: OS Independent
Classifier: Framework :: Django
Classifier: Intended Audience :: Developers
Classifier: Topic :: Internet :: WWW/HTTP :: Dynamic Content
